flask_pydantic_spec/__init__.py
flask_pydantic_spec/config.py
flask_pydantic_spec/constants.py
flask_pydantic_spec/flask_backend.py
flask_pydantic_spec/page.py
flask_pydantic_spec/spec.py
flask_pydantic_spec/types.py
flask_pydantic_spec/utils.py
flask_pydantic_spec-0.8.6.dist-info/licenses/LICENSE
flask_pydantic_spec-0.8.6.dist-info/METADATA
flask_pydantic_spec-0.8.6.dist-info/WHEEL
flask_pydantic_spec-0.8.6.dist-info/top_level.txt
flask_pydantic_spec-0.8.6.dist-info/RECORD
