Metadata-Version: 2.4
Name: flask_pydantic_spec
Version: 0.8.6
Summary: generate OpenAPI document and validate request & response with Python annotations.
Home-page: https://github.com/turner-townsend/flask-pydantic-spec
Author: Chris Gearing, Simon Hayward, Rob Young, Donald Fleming
Author-email: chris.gearing@turntown.digital
Classifier: Programming Language :: Python :: 3 :: Only
Classifier: Programming Language :: Python :: 3.9
Classifier: Programming Language :: Python :: 3.10
Classifier: Programming Language :: Python :: 3.11
Classifier: Programming Language :: Python :: 3.12
Classifier: Programming Language :: Python :: 3.13
Classifier: Operating System :: OS Independent
Classifier: Topic :: Software Development :: Libraries :: Python Modules
Requires-Python: >=3.9
License-File: LICENSE
Requires-Dist: pydantic>=2
Requires-Dist: inflection<1,>=0.5.0
Provides-Extra: flask
Requires-Dist: flask; extra == "flask"
Dynamic: author
Dynamic: author-email
Dynamic: classifier
Dynamic: description
Dynamic: description-content-type
Dynamic: home-page
Dynamic: license-file
Dynamic: provides-extra
Dynamic: requires-dist
Dynamic: requires-python
Dynamic: summary
